pyhiera/__init__.py
pyhiera/backends.py
pyhiera/errors.py
pyhiera/hiera.py
pyhiera/keys.py
pyhiera/models.py
pyhiera-0.0.0.dist-info/METADATA
pyhiera-0.0.0.dist-info/WHEEL
pyhiera-0.0.0.dist-info/licenses/LICENSE.txt
pyhiera-0.0.0.dist-info/RECORD
