Metadata-Version: 2.4
Name: pyhiera
Version: 0.0.0
Summary: PyHiera puppet hiera like parameter lookup engine
Project-URL: Repository, https://github.com/schlitzered/pyhiera
Project-URL: Issues, https://github.com/schlitzered/pyhiera/issues
Author-email: "Stephan.Schultchen" <stephan.schultchen@gmail.com>
License:                     GNU AFFERO GENERAL PUBLIC LICENSE
License-File: LICENSE.txt
Classifier: Programming Language :: Python
Requires-Python: >=3.9
Requires-Dist: aiofiles
Requires-Dist: pydantic
Requires-Dist: pyyaml
